gtasks2/__init__.py
gtasks2/gtaskobject.py
gtasks2/gtasks2.py
gtasks2/misc.py
gtasks2/task.py
gtasks2/tasklist.py
gtasks2/timeconversion.py
gtasks2-0.2.2.dist-info/LICENSE.txt
gtasks2-0.2.2.dist-info/METADATA
gtasks2-0.2.2.dist-info/WHEEL
gtasks2-0.2.2.dist-info/top_level.txt
gtasks2-0.2.2.dist-info/RECORD
