Metadata-Version: 2.1
Name: gtasks2
Version: 0.2.2
Summary: A fork from the greatest gtasks 
Home-page: https://github.com/BlueBlueBlob/Gtasks2
Author: BlueBlueBlob
Author-email: adrien.lesot@gmail.com
License: MIT
Keywords: google,tasks,task,gtasks,gtask
Platform: UNKNOWN
Requires-Dist: keyring
Requires-Dist: requests-oauthlib
